eb_metrics/__init__.py
eb_metrics/_utils.py
eb_metrics/frameworks/__init__.py
eb_metrics/frameworks/keras_loss.py
eb_metrics/frameworks/sklearn_scorer.py
eb_metrics/metrics/__init__.py
eb_metrics/metrics/loss.py
eb_metrics/metrics/regression.py
eb_metrics/metrics/service.py
eb_metrics-0.2.6.dist-info/licenses/LICENSE
eb_metrics-0.2.6.dist-info/METADATA
eb_metrics-0.2.6.dist-info/WHEEL
eb_metrics-0.2.6.dist-info/top_level.txt
eb_metrics-0.2.6.dist-info/RECORD
