Metadata-Version: 2.4
Name: eb-metrics
Version: 0.2.6
Summary: Core Electric Barometer error metrics, including asymmetric CWSL and standard forecast loss functions.
Author-email: "Kyle Corrie (Economistician)" <kcorrie@economistician.com>
License: BSD-3-Clause
Project-URL: Homepage, https://github.com/Economistician/eb-metrics
Project-URL: Repository, https://github.com/Economistician/eb-metrics
Project-URL: Issues, https://github.com/Economistician/eb-metrics/issues
Project-URL: Documentation, https://github.com/Economistician/eb-docs
Keywords: forecasting,metrics,evaluation,time-series,operations-research
Classifier: Development Status :: 3 - Alpha
Classifier: Intended Audience :: Science/Research
Classifier: Intended Audience :: Developers
Classifier: License :: OSI Approved :: BSD License
Classifier: Programming Language :: Python :: 3
Classifier: Programming Language :: Python :: 3.10
Classifier: Programming Language :: Python :: 3.11
Classifier: Programming Language :: Python :: 3.12
Classifier: Programming Language :: Python :: 3.13
Classifier: Operating System :: OS Independent
Classifier: Topic :: Scientific/Engineering
Requires-Python: >=3.10
License-File: LICENSE
Requires-Dist: numpy>=1.24
Provides-Extra: test
Requires-Dist: pytest>=8.0; extra == "test"
Requires-Dist: scikit-learn>=1.3; extra == "test"
Provides-Extra: dev
Requires-Dist: pytest>=8.0; extra == "dev"
Requires-Dist: pytest-cov>=5.0; extra == "dev"
Requires-Dist: ruff>=0.0.1; extra == "dev"
Requires-Dist: pyright>=1.1; extra == "dev"
Requires-Dist: twine>=4.0; extra == "dev"
Provides-Extra: sklearn
Requires-Dist: scikit-learn>=1.3; extra == "sklearn"
Provides-Extra: tf
Requires-Dist: tensorflow>=2.13; extra == "tf"
Provides-Extra: all
Requires-Dist: scikit-learn>=1.3; extra == "all"
Requires-Dist: tensorflow>=2.13; extra == "all"
Dynamic: license-file
